mdocx/__init__.py
mdocx-0.0.1.dist-info/LICENSE
mdocx-0.0.1.dist-info/METADATA
mdocx-0.0.1.dist-info/WHEEL
mdocx-0.0.1.dist-info/entry_points.txt
mdocx-0.0.1.dist-info/top_level.txt
mdocx-0.0.1.dist-info/RECORD
